Marketingtool/__init__.py
Marketingtool/__main__.py
Marketingtool/commandline.py
Marketingtool/common.py
Marketingtool/config.py
Marketingtool/core.py
Marketingtool/log.py
Marketingtool/tool_config.py
Marketingtool/version.py
Marketingtool/modules/__init__.py
Marketingtool/modules/audioprocess.py
Marketingtool/modules/get_watermark.py
Marketingtool/modules/translator.py
Marketingtool/modules/videoedit.py
Marketingtool/modules/watermark.py
Tests/__init__.py
Tests/test_videoedit.py
Tests/test_watermark.py
Tests/translator_tests.py
Marketingtool-1.0.11.dist-info/LICENSE.txt
Marketingtool-1.0.11.dist-info/METADATA
Marketingtool-1.0.11.dist-info/WHEEL
Marketingtool-1.0.11.dist-info/entry_points.txt
Marketingtool-1.0.11.dist-info/top_level.txt
Marketingtool-1.0.11.dist-info/RECORD
